LICENSE.rst
MANIFEST.in
Makefile
README.rst
setup.cfg
setup.py
Brownie.egg-info/PKG-INFO
Brownie.egg-info/SOURCES.txt
Brownie.egg-info/dependency_links.txt
Brownie.egg-info/not-zip-safe
Brownie.egg-info/top_level.txt
brownie/__init__.py
brownie/abstract.py
brownie/caching.py
brownie/functional.py
brownie/importing.py
brownie/itools.py
brownie/parallel.py
brownie/proxies.py
brownie/pycompat.py
brownie/tests/__init__.py
brownie/tests/abstract.py
brownie/tests/caching.py
brownie/tests/importing.py
brownie/tests/itools.py
brownie/tests/parallel.py
brownie/tests/proxies.py
docs/Makefile
docs/abstract.rst
docs/authors.rst
docs/caching.rst
docs/changelog.rst
docs/conf.py
docs/contributing.rst
docs/datastructures.rst
docs/designdefence.rst
docs/functional.rst
docs/importing.rst
docs/index.rst
docs/itools.rst
docs/license.rst
docs/make.bat
docs/parallel.rst
docs/proxies.rst
docs/testing.rst
docs/_themes/minimalism/.gitignore
docs/_themes/minimalism/README
docs/_themes/minimalism/layout.html
docs/_themes/minimalism/relations.html
docs/_themes/minimalism/theme.conf
docs/_themes/minimalism/theme_style.py
docs/_themes/minimalism/theme_style.pyc
docs/_themes/minimalism/.git/COMMIT_EDITMSG
docs/_themes/minimalism/.git/HEAD
docs/_themes/minimalism/.git/config
docs/_themes/minimalism/.git/description
docs/_themes/minimalism/.git/index
docs/_themes/minimalism/.git/packed-refs
docs/_themes/minimalism/.git/hooks/applypatch-msg.sample
docs/_themes/minimalism/.git/hooks/commit-msg.sample
docs/_themes/minimalism/.git/hooks/post-commit.sample
docs/_themes/minimalism/.git/hooks/post-receive.sample
docs/_themes/minimalism/.git/hooks/post-update.sample
docs/_themes/minimalism/.git/hooks/pre-applypatch.sample
docs/_themes/minimalism/.git/hooks/pre-commit.sample
docs/_themes/minimalism/.git/hooks/pre-rebase.sample
docs/_themes/minimalism/.git/hooks/prepare-commit-msg.sample
docs/_themes/minimalism/.git/hooks/update.sample
docs/_themes/minimalism/.git/info/exclude
docs/_themes/minimalism/.git/logs/HEAD
docs/_themes/minimalism/.git/logs/refs/heads/master
docs/_themes/minimalism/.git/logs/refs/remotes/origin/master
