Metadata-Version: 1.0
Name: Brownie
Version: 0.5
Summary: Common utilities and datastructures for Python applications.
Home-page: http://github.com/DasIch/brownie/
Author: Daniel Neuhäuser
Author-email: dasdasich@gmail.com
License: BSD
Platform: any
Classifier: Intended Audience :: Developers
Classifier: License :: OSI Approved :: BSD License
Classifier: Operating System :: OS Independent
Classifier: Programming Language :: Python
Classifier: Programming Language :: Python :: 2
Classifier: Programming Language :: Python :: 2.5
Classifier: Programming Language :: Python :: 2.6
Classifier: Programming Language :: Python :: 2.7
Classifier: Topic :: Software Development :: Libraries
